{
	"districts" : [
		{
			"code_district" : 40001,
			"value_district" : "Dakar-Plateau",
			"code_department" : 20001 
		},
		{
			"code_district" : 40002,
			"value_district" : "Grand Dakar",
			"code_department" : 20001
		},
		{
			"code_district" : 40003,
			"value_district" : "Almadies",
			"code_department" : 20001 
		},
		{
			"code_district" : 40004,
			"value_district" : "Parcelles Assainies",
			"code_department" : 20001
		},
		{
			"code_district" : 40005,
			"value_district" : "Commune-Department",
			"code_department" : 20001
		},
		{
			"code_district" : 40006,
			"value_district" : "Guediawaye",
			"code_department" : 20002 
		},
		{
			"code_district" : 40007,
			"value_district" : "Commune-Department",
			"code_department" : 20002
		},
		{
			"code_district" : 40008,
			"value_district" : "Thiaroye",
			"code_department" : 20003 
		},
		{
			"code_district" : 40009,
			"value_district" : "Niayes",
			"code_department" : 20003
		},
		{
			"code_district" : 40010,
			"value_district" : "Pikine Dagoudane",
			"code_department" : 20003
		},
		{
			"code_district" : 40011,
			"value_district" : "Commune-Department",
			"code_department" : 20003
		},
		{
			"code_district" : 40012,
			"value_district" : "Rufisque-Est",
			"code_department" : 20004
		},
		{
			"code_district" : 40013,
			"value_district" : "Bambylor",
			"code_department" : 20004
		},
		{
			"code_district" : 40014,
			"value_district" : "Commune-Department",
			"code_department" : 20004
		},
		{
			"code_district" : 40015,
			"value_district" : "Baba Garage",
			"code_department" : 20005
		},
		{
			"code_district" : 40016,
			"value_district" : "Ngoye",
			"code_department" : 20005
		},
		{
			"code_district" : 40017,
			"value_district" : "Lambaye",
			"code_department" : 20005
		},
		{
			"code_district" : 40018,
			"value_district" : "Commune-Department",
			"code_department" : 20005
		},
		{
			"code_district" : 40019,
			"value_district" : "Ndoulo",
			"code_department" : 20006
		},
		{
			"code_district" : 40020,
			"value_district" : "Ndindy",
			"code_department" : 20006
		},
		{
			"code_district" : 40021,
			"value_district" : "Commune-Department",
			"code_department" : 20006
		},
		{
			"code_district" : 40022,
			"value_district" : "Ndame",
			"code_department" : 20007
		},
		{
			"code_district" : 40023,
			"value_district" : "Kael",
			"code_department" : 20007
		},
		{
			"code_district" : 40024,
			"value_district" : "Taif",
			"code_department" : 20007
		},
		{
			"code_district" : 40025,
			"value_district" : "Commune-Department",
			"code_department" : 20007
		},
		{
			"code_district" : 40026,
			"value_district" : "Ndiop",
			"code_department" : 20008
		},
		{
			"code_district" : 40027,
			"value_district" : "Fimela",
			"code_department" : 20008
		},
		{
			"code_district" : 40028,
			"value_district" : "Niakhar",
			"code_department" : 20008
		},
		{
			"code_district" : 40029,
			"value_district" : "Tattaguine",
			"code_department" : 20008
		},
		{
			"code_district" : 40030,
			"value_district" : "Commune-Department",
			"code_department" : 20008
		},
		{
			"code_district" : 40031,
			"value_district" : "Toubacouta",
			"code_department" : 20009
		},
		{
			"code_district" : 40032,
			"value_district" : "Djilor",
			"code_department" : 20009
		},
		{
			"code_district" : 40033,
			"value_district" : "Niodior",
			"code_department" : 20009
		},
		{
			"code_district" : 40034,
			"value_district" : "Commune-Department",
			"code_department" : 20009
		},
		{
			"code_district" : 40035,
			"value_district" : "Colobane",
			"code_department" : 20010
		},
		{
			"code_district" : 40036,
			"value_district" : "Ouadiour",
			"code_department" : 20010
		},
		{
			"code_district" : 40037,
			"value_district" : "Commune-Department",
			"code_department" : 20010
		},
		{
			"code_district" : 40038,
			"value_district" : "Keur Mboucki",
			"code_department" : 20011
		},
		{
			"code_district" : 40039,
			"value_district" : "Mabo",
			"code_department" : 20011
		},
		{
			"code_district" : 40040,
			"value_district" : "Commune-Department",
			"code_department" : 20011
		},
		{
			"code_district" : 40041,
			"value_district" : "Katakel",
			"code_department" : 20012
		},
		{
			"code_district" : 40042,
			"value_district" : "Gniby",
			"code_department" : 20012
		},
		{
			"code_district" : 40043,
			"value_district" : "Commune-Department",
			"code_department" : 20012
		},
		{
			"code_district" : 40044,
			"value_district" : "Missirah Wadene",
			"code_department" : 20013
		},
		{
			"code_district" : 40045,
			"value_district" : "Ida Mouride",
			"code_department" : 20013
		},
		{
			"code_district" : 40046,
			"value_district" : "Lour escale",
			"code_department" : 20013
		},
		{
			"code_district" : 40047,
			"value_district" : "Commune-Department",
			"code_department" : 20013
		},
		{
			"code_district" : 40048,
			"value_district" : "Darou Minam 2",
			"code_department" : 20014
		},
		{
			"code_district" : 40049,
			"value_district" : "Sagna",
			"code_department" : 20014
		},
		{
			"code_district" : 40050,
			"value_district" : "Commune-Department",
			"code_department" : 20014
		},
		{
			"code_district" : 40051,
			"value_district" : "Mbadakhoune",
			"code_department" : 20015
		},
		{
			"code_district" : 40052,
			"value_district" : "Nguelou",
			"code_department" : 20015
		},
		{
			"code_district" : 40053,
			"value_district" : "Commune-Department",
			"code_department" : 20015
		},
		{
			"code_district" : 40054,
			"value_district" : "Koumbal",
			"code_department" : 20016
		},
		{
			"code_district" : 40055,
			"value_district" : "Ndiedieng",
			"code_department" : 20016
		},
		{
			"code_district" : 40056,
			"value_district" : "Ngothie",
			"code_department" : 20016
		},
		{
			"code_district" : 40057,
			"value_district" : "Commune-Department",
			"code_department" : 20016
		},
		{
			"code_district" : 40058,
			"value_district" : "Medina Sabakh",
			"code_department" : 20017
		},
		{
			"code_district" : 40059,
			"value_district" : "Paos koto",
			"code_department" : 20017
		},
		{
			"code_district" : 40060,
			"value_district" : "Wack Ngouna",
			"code_department" : 20017
		},
		{
			"code_district" : 40061,
			"value_district" : "Commune-Department",
			"code_department" : 20017
		},
		{
			"code_district" : 40062,
			"value_district" : "Bandafassi",
			"code_department" : 20018
		},
		{
			"code_district" : 40063,
			"value_district" : "Fongolimbi",
			"code_department" : 20018
		},
		{
			"code_district" : 40064,
			"value_district" : "Commune-Department",
			"code_department" : 20018
		},
		{
			"code_district" : 40065,
			"value_district" : "Dakateli",
			"code_department" : 20019
		},
		{
			"code_district" : 40066,
			"value_district" : "Dar Salam",
			"code_department" : 20019
		},
		{
			"code_district" : 40067,
			"value_district" : "Commune-Department",
			"code_department" : 20019
		},
		{
			"code_district" : 40068,
			"value_district" : "Bembou",
			"code_department" : 20020
		},
		{
			"code_district" : 40069,
			"value_district" : "Sabodala",
			"code_department" : 20020
		},
		{
			"code_district" : 40070,
			"value_district" : "Commune-Department",
			"code_department" : 20020
		},
		{
			"code_district" : 40071,
			"value_district" : "Mampatim",
			"code_department" : 20021
		},
		{
			"code_district" : 40072,
			"value_district" : "Sare Bidji",
			"code_department" : 20021
		},
		{
			"code_district" : 40073,
			"value_district" : "Dioulacolon",
			"code_department" : 20021
		},
		{
			"code_district" : 40074,
			"value_district" : "Commune-Department",
			"code_department" : 20021
		},
		{
			"code_district" : 40075,
			"value_district" : "Fafacourou",
			"code_department" : 20022
		},
		{
			"code_district" : 40076,
			"value_district" : "Ndorna",
			"code_department" : 20022
		},
		{
			"code_district" : 40077,
			"value_district" : "Niaming",
			"code_department" : 20022
		},
		{
			"code_district" : 40078,
			"value_district" : "Commune-Department",
			"code_department" : 20022
		},
		{
			"code_district" : 40079,
			"value_district" : "Sare Coly Salle",
			"code_department" : 20023
		},
		{
			"code_district" : 40080,
			"value_district" : "Pakour",
			"code_department" : 20023
		},
		{
			"code_district" : 40081,
			"value_district" : "Bonconto",
			"code_department" : 20023
		},
		{
			"code_district" : 40082,
			"value_district" : "Commune-Department",
			"code_department" : 20023
		},
		{
			"code_district" : 40083,
			"value_district" : "Ndande",
			"code_department" : 20024
		},
		{
			"code_district" : 40084,
			"value_district" : "Darou Mousty",
			"code_department" : 20024
		},
		{
			"code_district" : 40085,
			"value_district" : "Sagatta",
			"code_department" : 20024
		},
		{
			"code_district" : 40086,
			"value_district" : "Commune-Department",
			"code_department" : 20024
		},
		{
			"code_district" : 40087,
			"value_district" : "Barkedji",
			"code_department" : 20025
		},
		{
			"code_district" : 40088,
			"value_district" : "Sagatta Djolof",
			"code_department" : 20025
		},
		{
			"code_district" : 40089,
			"value_district" : "Dodji",
			"code_department" : 20025
		},
		{
			"code_district" : 40090,
			"value_district" : "Yang yang",
			"code_department" : 20025
		},
		{
			"code_district" : 40091,
			"value_district" : "Commune-Department",
			"code_department" : 20025
		},
		{
			"code_district" : 40092,
			"value_district" : "Coki",
			"code_department" : 20026
		},
		{
			"code_district" : 40093,
			"value_district" : "Keur Momar Sarr",
			"code_department" : 20026
		},
		{
			"code_district" : 40094,
			"value_district" : "Mbediene",
			"code_department" : 20026
		},
		{
			"code_district" : 40095,
			"value_district" : "Sakal",
			"code_department" : 20026
		},
		{
			"code_district" : 40096,
			"value_district" : "Commune-Department",
			"code_department" : 20026
		},
		{
			"code_district" : 40097,
			"value_district" : "Wouro Sidy",
			"code_department" : 20027
		},
		{
			"code_district" : 40098,
			"value_district" : "Orkadiere",
			"code_department" : 20027
		},
		{
			"code_district" : 40099,
			"value_district" : "Commune-Department",
			"code_department" : 20027
		},
		{
			"code_district" : 40100,
			"value_district" : "Agnam Civol",
			"code_department" : 20028
		},
		{
			"code_district" : 40101,
			"value_district" : "Ogo",
			"code_department" : 20028
		},
		{
			"code_district" : 40102,
			"value_district" : "Commune-Department",
			"code_department" : 20028
		},
		{
			"code_district" : 40103,
			"value_district" : "Velingra",
			"code_department" : 20029
		},
		{
			"code_district" : 40104,
			"value_district" : "Commune-Department",
			"code_department" : 20029
		},
		{
			"code_district" : 40105,
			"value_district" : "Ndiaye",
			"code_department" : 20030
		},
		{
			"code_district" : 40106,
			"value_district" : "Mbane",
			"code_department" : 20030
		},
		{
			"code_district" : 40107,
			"value_district" : "Commune-Department",
			"code_department" : 20030
		},
		{
			"code_district" : 40108,
			"value_district" : "Cas Cas",
			"code_department" : 20031
		},
		{
			"code_district" : 40109,
			"value_district" : "Gamadji Sare",
			"code_department" : 20031
		},
		{
			"code_district" : 40110,
			"value_district" : "Thile Boubacar",
			"code_department" : 20031
		},
		{
			"code_district" : 40111,
			"value_district" : "Salde",
			"code_department" : 20031
		},
		{
			"code_district" : 40112,
			"value_district" : "Commune-Department",
			"code_department" : 20031
		},
		{
			"code_district" : 40113,
			"value_district" : "Rao",
			"code_department" : 20032
		},
		{
			"code_district" : 40114,
			"value_district" : "Commune-Department",
			"code_department" : 20032
		},
		{
			"code_district" : 40115,
			"value_district" : "Boghal",
			"code_department" : 20033
		},
		{
			"code_district" : 40116,
			"value_district" : "Bona",
			"code_department" : 20033
		},
		{
			"code_district" : 40117,
			"value_district" : "Diaroume",
			"code_department" : 20033
		},
		{
			"code_district" : 40118,
			"value_district" : "Commune-Department",
			"code_department" : 20033
		},
		{
			"code_district" : 40119,
			"value_district" : "Djibanar",
			"code_department" : 20034
		},
		{
			"code_district" : 40120,
			"value_district" : "Simbandi Brassou",
			"code_department" : 20034
		},
		{
			"code_district" : 40121,
			"value_district" : "Karantaba",
			"code_department" : 20034
		},
		{
			"code_district" : 40122,
			"value_district" : "Commune-Department",
			"code_department" : 20034
		},
		{
			"code_district" : 40123,
			"value_district" : "Djiredji",
			"code_department" : 20035
		},
		{
			"code_district" : 40124,
			"value_district" : "Diende",
			"code_department" : 20035
		},
		{
			"code_district" : 40125,
			"value_district" : "Djibabouya",
			"code_department" : 20035
		},
		{
			"code_district" : 40126,
			"value_district" : "Commune-Department",
			"code_department" : 20035
		},
		{
			"code_district" : 40127,
			"value_district" : "Bele",
			"code_department" : 20036
		},
		{
			"code_district" : 40128,
			"value_district" : "Kenieba",
			"code_department" : 20036
		},
		{
			"code_district" : 40129,
			"value_district" : "Moudery",
			"code_department" : 20036
		},
		{
			"code_district" : 40130,
			"value_district" : "Commune-Department",
			"code_department" : 20036
		},
		{
			"code_district" : 40131,
			"value_district" : "Boynguel Bamba",
			"code_department" : 20037
		},
		{
			"code_district" : 40132,
			"value_district" : "Dianke Makha",
			"code_department" : 20037
		},
		{
			"code_district" : 40133,
			"value_district" : "Koulor",
			"code_department" : 20037
		},
		{
			"code_district" : 40134,
			"value_district" : "Bala",
			"code_department" : 20037
		},
		{
			"code_district" : 40135,
			"value_district" : "Commune-Department",
			"code_department" : 20037
		},
		{
			"code_district" : 40136,
			"value_district" : "Bamba Thialene",
			"code_department" : 20038
		},
		{
			"code_district" : 40137,
			"value_district" : "Kouthiaba wolof",
			"code_department" : 20038
		},
		{
			"code_district" : 40138,
			"value_district" : "Commune-Department",
			"code_department" : 20038
		},
		{
			"code_district" : 40139,
			"value_district" : "Makacolibanta",
			"code_department" : 20039
		},
		{
			"code_district" : 40140,
			"value_district" : "Missirah",
			"code_department" : 20039
		},
		{
			"code_district" : 40141,
			"value_district" : "Koussanar",
			"code_department" : 20039
		},
		{
			"code_district" : 40142,
			"value_district" : "Commune-Department",
			"code_department" : 20039
		},
		{
			"code_district" : 40143,
			"value_district" : "Fissel",
			"code_department" : 20040
		},
		{
			"code_district" : 40144,
			"value_district" : "Sessene",
			"code_department" : 20040
		},
		{
			"code_district" : 40145,
			"value_district" : "Sindia",
			"code_department" : 20040
		},
		{
			"code_district" : 40146,
			"value_district" : "Commune-Department",
			"code_department" : 20040
		},
		{
			"code_district" : 40147,
			"value_district" : "Thies Nord",
			"code_department" : 20041
		},
		{
			"code_district" : 40148,
			"value_district" : "Thies Sud",
			"code_department" : 20041
		},
		{
			"code_district" : 40149,
			"value_district" : "Thienaba",
			"code_department" : 20041
		},
		{
			"code_district" : 40150,
			"value_district" : "Keur Moussa",
			"code_department" : 20041
		},
		{
			"code_district" : 40151,
			"value_district" : "Notto",
			"code_department" : 20041
		},
		{
			"code_district" : 40152,
			"value_district" : "Commune-Department",
			"code_department" : 20041
		},
		{
			"code_district" : 40153,
			"value_district" : "Meouane",
			"code_department" : 20042
		},
		{
			"code_district" : 40154,
			"value_district" : "Merina Dakhar",
			"code_department" : 20042
		},
		{
			"code_district" : 40155,
			"value_district" : "Niakhene",
			"code_department" : 20042
		},
		{
			"code_district" : 40156,
			"value_district" : "Pambal",
			"code_department" : 20042
		},
		{
			"code_district" : 40157,
			"value_district" : "Commune-Department",
			"code_department" : 20042
		},
		{
			"code_district" : 40158,
			"value_district" : "Niaguis",
			"code_department" : 20043
		},
		{
			"code_district" : 40159,
			"value_district" : "Niassia",
			"code_department" : 20043
		},
		{
			"code_district" : 40160,
			"value_district" : "Commune-Department",
			"code_department" : 20043
		},
		{
			"code_district" : 40161,
			"value_district" : "Cabrousse",
			"code_department" : 20044
		},
		{
			"code_district" : 40162,
			"value_district" : "Loudia Ouolof",
			"code_department" : 20044
		},
		{
			"code_district" : 40163,
			"value_district" : "Commune-Department",
			"code_department" : 20044
		},
		{
			"code_district" : 40164,
			"value_district" : "Kataba 1",
			"code_department" : 20045
		},
		{
			"code_district" : 40165,
			"value_district" : "Tenghori",
			"code_department" : 20045
		},
		{
			"code_district" : 40166,
			"value_district" : "Tendouck",
			"code_department" : 20045
		},
		{
			"code_district" : 40167,
			"value_district" : "Sindian",
			"code_department" : 20045
		},
		{
			"code_district" : 40168,
			"value_district" : "Commune-Department",
			"code_department" : 20045
		}
	]
}